__init__.py
seeker.py
insideopt_seeker-0.3.dist-info/METADATA
insideopt_seeker-0.3.dist-info/WHEEL
insideopt_seeker-0.3.dist-info/top_level.txt
insideopt_seeker-0.3.dist-info/RECORD
