Metadata-Version: 2.1
Name: insideopt-seeker
Version: 0.3
Summary: A module for stochastic non-linear optimization
Author: Meinolf Sellmann
Author-email: meinolf@gmail.com
